{
  "identityPoolName": "datn5b88ddfe_identitypool_5b88ddfe",
  "allowUnauthenticatedIdentities": false,
  "resourceNameTruncated": "datn5b88ddfe",
  "userPoolName": "datn5b88ddfe_userpool_5b88ddfe",
  "autoVerifiedAttributes": [
    "email"
  ],
  "mfaConfiguration": "OFF",
  "mfaTypes": [
    "SMS Text Message"
  ],
  "smsAuthenticationMessage": "Your authentication code is {####}",
  "smsVerificationMessage": "Your verification code is {####}",
  "emailVerificationSubject": "Your verification code",
  "emailVerificationMessage": "Your verification code is {####}",
  "defaultPasswordPolicy": false,
  "passwordPolicyMinLength": 8,
  "passwordPolicyCharacters": [],
  "requiredAttributes": [
    "email"
  ],
  "aliasAttributes": [],
  "userpoolClientGenerateSecret": false,
  "userpoolClientRefreshTokenValidity": 30,
  "userpoolClientWriteAttributes": [
    "email"
  ],
  "userpoolClientReadAttributes": [
    "email"
  ],
  "userpoolClientLambdaRole": "datn5b5b88ddfe_userpoolclient_lambda_role",
  "userpoolClientSetAttributes": false,
  "sharedId": "5b88ddfe",
  "resourceName": "datn5b88ddfe",
  "authSelections": "identityPoolAndUserPool",
  "useDefault": "default",
  "userPoolGroupList": [],
  "serviceName": "Cognito",
  "usernameCaseSensitive": false,
  "useEnabledMfas": true,
  "authRoleArn": {
    "Fn::GetAtt": [
      "AuthRole",
      "Arn"
    ]
  },
  "unauthRoleArn": {
    "Fn::GetAtt": [
      "UnauthRole",
      "Arn"
    ]
  },
  "breakCircularDependency": true,
  "dependsOn": []
}